gview/G_VAR.py
gview/Hosts.txt
gview/__init__.py
gview/__main__.py
gview/app.py
gview/app_celery_init.py
gview/host.py
gview/index.py
gview/p_worker.py
gview/plotDataAPI.py
gview/run.py
gview/run.sh
gview/utils.py
gview/worker.py
gview/wsgi.py
gview/static/css/base.css
gview/static/css/host.css
gview/static/css/indexLoading.css
gview/static/js/HostData.json
gview/static/js/vue.min.js
gview/templates/host.html
gview/templates/index.html
gview-0.0.10.dist-info/LICENSE
gview-0.0.10.dist-info/METADATA
gview-0.0.10.dist-info/WHEEL
gview-0.0.10.dist-info/entry_points.txt
gview-0.0.10.dist-info/top_level.txt
gview-0.0.10.dist-info/RECORD
