Metadata-Version: 2.1
Name: gview
Version: 0.0.10
Summary: a RESTful web application to monitor GPU usage across multiple servers
Author: Brandon S
Author-email: brankond@gmail.com
License: UNKNOWN
Platform: UNKNOWN
License-File: LICENSE
